gshap/__init__.py
gshap/hypothesis.py
gshap/intergroup.py
gshap/performance.py
gshap/probability_distance.py
gshap/utils.py
gshap/datasets/__init__.py
gshap/datasets/compas/two-year-recidivism.csv
gshap/datasets/gdp/GDP-growth.csv
gshap-0.0.3.dist-info/LICENSE
gshap-0.0.3.dist-info/METADATA
gshap-0.0.3.dist-info/WHEEL
gshap-0.0.3.dist-info/top_level.txt
gshap-0.0.3.dist-info/RECORD
