Metadata-Version: 2.1
Name: gshap
Version: 0.0.3
Summary: A technique in explainable AI for answering broader questions in machine learning.
Home-page: https://dsbowen.github.io/gshap
Author: Dillon Bowen
Author-email: dsbowen@wharton.upenn.edu
License: UNKNOWN
Platform: UNKNOWN
Classifier: Programming Language :: Python :: 3
Classifier: License :: OSI Approved :: MIT License
Classifier: Operating System :: OS Independent
Requires-Python: >=3.6
Requires-Dist: numpy (>=1.18.4)
Requires-Dist: pandas (>=1.0.3)
